cuqi/__init__.py
cuqi/_messages.py
cuqi/_version.py
cuqi/config.py
cuqi/diagnostics.py
cuqi/algebra/__init__.py
cuqi/algebra/_abstract_syntax_tree.py
cuqi/algebra/_ordered_set.py
cuqi/algebra/_random_variable.py
cuqi/array/__init__.py
cuqi/array/_array.py
cuqi/data/__init__.py
cuqi/data/_data.py
cuqi/data/astronaut.npz
cuqi/data/camera.npz
cuqi/data/cat.npz
cuqi/data/cookie.png
cuqi/data/satellite.mat
cuqi/density/__init__.py
cuqi/density/_density.py
cuqi/distribution/__init__.py
cuqi/distribution/_beta.py
cuqi/distribution/_cauchy.py
cuqi/distribution/_cmrf.py
cuqi/distribution/_custom.py
cuqi/distribution/_distribution.py
cuqi/distribution/_gamma.py
cuqi/distribution/_gaussian.py
cuqi/distribution/_gmrf.py
cuqi/distribution/_inverse_gamma.py
cuqi/distribution/_joint_distribution.py
cuqi/distribution/_laplace.py
cuqi/distribution/_lmrf.py
cuqi/distribution/_lognormal.py
cuqi/distribution/_modified_half_normal.py
cuqi/distribution/_normal.py
cuqi/distribution/_posterior.py
cuqi/distribution/_smoothed_laplace.py
cuqi/distribution/_truncated_normal.py
cuqi/distribution/_uniform.py
cuqi/experimental/__init__.py
cuqi/experimental/_recommender.py
cuqi/geometry/__init__.py
cuqi/geometry/_geometry.py
cuqi/geometry/_product_geometry.py
cuqi/implicitprior/__init__.py
cuqi/implicitprior/_regularized_gaussian.py
cuqi/implicitprior/_regularized_gmrf.py
cuqi/implicitprior/_regularized_unbounded_uniform.py
cuqi/implicitprior/_restorator.py
cuqi/legacy/__init__.py
cuqi/legacy/sampler/__init__.py
cuqi/legacy/sampler/_conjugate.py
cuqi/legacy/sampler/_conjugate_approx.py
cuqi/legacy/sampler/_cwmh.py
cuqi/legacy/sampler/_gibbs.py
cuqi/legacy/sampler/_hmc.py
cuqi/legacy/sampler/_langevin_algorithm.py
cuqi/legacy/sampler/_laplace_approximation.py
cuqi/legacy/sampler/_mh.py
cuqi/legacy/sampler/_pcn.py
cuqi/legacy/sampler/_rto.py
cuqi/legacy/sampler/_sampler.py
cuqi/likelihood/__init__.py
cuqi/likelihood/_likelihood.py
cuqi/model/__init__.py
cuqi/model/_model.py
cuqipy-1.5.0.dist-info/licenses/LICENSE
cuqipy-1.5.0.dist-info/METADATA
cuqipy-1.5.0.dist-info/WHEEL
cuqipy-1.5.0.dist-info/top_level.txt
cuqipy-1.5.0.dist-info/RECORD
