Metadata-Version: 2.4
Name: CUQIpy
Version: 1.5.0
Summary: Computational Uncertainty Quantification for Inverse problems in Python
Maintainer-email: "Nicolai A. B. Riis" <nabr@dtu.dk>, "Jakob S. Jørgensen" <jakj@dtu.dk>, "Amal M. Alghamdi" <amaal@dtu.dk>, Chao Zhang <chaz@dtu.dk>
License:                                  Apache License
Project-URL: Source, https://github.com/CUQI-DTU/CUQIpy
Project-URL: Documentation, https://cuqi-dtu.github.io/CUQIpy/
Project-URL: Download, https://github.com/CUQI-DTU/CUQIpy/releases
Project-URL: Tracker, https://github.com/CUQI-DTU/CUQIpy/issues
Requires-Python: >=3.9
License-File: LICENSE
Requires-Dist: matplotlib
Requires-Dist: numpy<=2.2.0
Requires-Dist: scipy==1.12.0; python_version <= "3.9"
Requires-Dist: scipy; python_version > "3.9"
Requires-Dist: arviz
Requires-Dist: tqdm
Dynamic: license-file
